docs/source/conf.py
skysegmentor/__init__.py
skysegmentor/coords.py
skysegmentor/groupfinder.py
skysegmentor/maths.py
skysegmentor/partition.py
skysegmentor/rotate.py
skysegmentor/utils.py
skysegmentor-1.0.0.dist-info/licenses/LICENSE.txt
skysegmentor-1.0.0.dist-info/METADATA
skysegmentor-1.0.0.dist-info/WHEEL
skysegmentor-1.0.0.dist-info/top_level.txt
skysegmentor-1.0.0.dist-info/RECORD
