Metadata-Version: 2.4
Name: skysegmentor
Version: 1.0.0
Summary: SkySegmentor: Splits a binary map into several regions using the binary space partition algorithm.
Author-email: Krishna Naidoo <krishna.naidoo.11@ucl.ac.uk>
Maintainer-email: Krishna Naidoo <krishna.naidoo.11@ucl.ac.uk>
License: MIT
Project-URL: Homepage, https://github.com/knaidoo29/SkySegmentor
Project-URL: Repository, https://github.com/knaidoo29/SkySegmentor
Project-URL: Documentation, https://skysegmentor.readthedocs.io/en/latest/
Project-URL: Bug Tracker, https://github.com/knaidoo29/SkySegmentor/issues
Project-URL: Changelog, https://github.com/knaidoo29/SkySegmentor/blob/main/CHANGELOG.md
Keywords: astronomy,partitioning,skymaps
Classifier: Development Status :: 4 - Beta
Classifier: Intended Audience :: Developers
Classifier: Intended Audience :: Science/Research
Classifier: Natural Language :: English
Classifier: Programming Language :: Python :: 3
Classifier: Programming Language :: Python :: 3.7
Classifier: Programming Language :: Python :: 3.8
Classifier: Programming Language :: Python :: 3.9
Classifier: Programming Language :: Python :: 3.10
Classifier: Programming Language :: Python :: 3.11
Classifier: Programming Language :: Python :: 3.12
Classifier: Topic :: Scientific/Engineering :: Astronomy
Classifier: Topic :: Scientific/Engineering :: Mathematics
Classifier: Topic :: Scientific/Engineering
Requires-Python: >=3.7
License-File: LICENSE.txt
Requires-Dist: numpy<1.27,>=1.22
Requires-Dist: healpy>=1.15.0
Provides-Extra: dev
Requires-Dist: black; extra == "dev"
Requires-Dist: flake8; extra == "dev"
Requires-Dist: ipython; extra == "dev"
Requires-Dist: jupyter; extra == "dev"
Requires-Dist: mypy; extra == "dev"
Provides-Extra: docs
Requires-Dist: numpydoc; extra == "docs"
Requires-Dist: sphinx; extra == "docs"
Requires-Dist: sphinx-rtd-theme; extra == "docs"
Provides-Extra: test
Requires-Dist: nose; extra == "test"
Requires-Dist: pytest>=6.0; extra == "test"
Requires-Dist: pytest-cov; extra == "test"
Dynamic: license-file
